odoo/addons/base_cron_oneshot/README.rst
odoo/addons/base_cron_oneshot/__init__.py
odoo/addons/base_cron_oneshot/__manifest__.py
odoo/addons/base_cron_oneshot/data/ir_cron.xml
odoo/addons/base_cron_oneshot/data/ir_sequence.xml
odoo/addons/base_cron_oneshot/i18n/base_cron_oneshot.pot
odoo/addons/base_cron_oneshot/models/__init__.py
odoo/addons/base_cron_oneshot/models/ir_cron.py
odoo/addons/base_cron_oneshot/readme/CONTRIBUTORS.rst
odoo/addons/base_cron_oneshot/readme/DESCRIPTION.rst
odoo/addons/base_cron_oneshot/readme/HISTORY.rst
odoo/addons/base_cron_oneshot/readme/USAGE.rst
odoo/addons/base_cron_oneshot/static/description/icon.png
odoo/addons/base_cron_oneshot/static/description/index.html
odoo/addons/base_cron_oneshot/tests/__init__.py
odoo/addons/base_cron_oneshot/tests/test_cron.py
odoo/addons/base_cron_oneshot/views/ir_cron.xml
odoo11_addon_base_cron_oneshot-11.0.1.0.0.99.dev10.dist-info/METADATA
odoo11_addon_base_cron_oneshot-11.0.1.0.0.99.dev10.dist-info/WHEEL
odoo11_addon_base_cron_oneshot-11.0.1.0.0.99.dev10.dist-info/top_level.txt
odoo11_addon_base_cron_oneshot-11.0.1.0.0.99.dev10.dist-info/RECORD
